dispatch/__init__.py
dispatch/debug.py
dispatch/list.py
dispatch/main.py
dispatch/net.py
dispatch/server.py
dispatch/socks.py
dispatch/test_connection.py
dispatch/dispatcher/__init__.py
dispatch/dispatcher/base.py
dispatch/dispatcher/weighted_rr.py
dispatch_proxy-1.0.9.dist-info/licenses/LICENSE.md
dispatch_proxy-1.0.9.dist-info/METADATA
dispatch_proxy-1.0.9.dist-info/WHEEL
dispatch_proxy-1.0.9.dist-info/entry_points.txt
dispatch_proxy-1.0.9.dist-info/top_level.txt
dispatch_proxy-1.0.9.dist-info/RECORD
