Metadata-Version: 2.4
Name: dispatch-proxy
Version: 1.0.9
Summary: A SOCKS proxy that balances traffic between network interfaces
Author-email: tboy1337 <obywhuie@anonaddy.com>
License: Commercial Restricted License (CRL)
Project-URL: Homepage, https://github.com/tboy1337/dispatch-py
Project-URL: Bug Tracker, https://github.com/tboy1337/dispatch-py/issues
Project-URL: Download, https://github.com/tboy1337/dispatch-py/releases/latest
Classifier: Development Status :: 4 - Beta
Classifier: Intended Audience :: Developers
Classifier: Programming Language :: Python :: 3
Classifier: Programming Language :: Python :: 3.7
Classifier: Programming Language :: Python :: 3.8
Classifier: Programming Language :: Python :: 3.9
Classifier: Programming Language :: Python :: 3.10
Requires-Python: >=3.7
License-File: LICENSE.md
Requires-Dist: asyncio
Requires-Dist: click
Requires-Dist: colorama
Requires-Dist: netifaces
Requires-Dist: python-socks
Requires-Dist: async-timeout
Requires-Dist: dnspython
Requires-Dist: ipaddress
Requires-Dist: typing_extensions
Requires-Dist: psutil
Requires-Dist: PySocks
Dynamic: license-file
